chameleontools/ChromatoSeq/_ChromatoSeq.py
chameleontools/ChromatoSeq/__init__.py
chameleontools/CodonAnalyzer/_CodonAnalyzer.py
chameleontools/CodonAnalyzer/__init__.py
chameleontools/FastAreader/_FastAreader.py
chameleontools/FastAreader/__init__.py
chameleontools/ORFfinder/_ORFfinder.py
chameleontools/ORFfinder/__init__.py
chameleontools/SeqParser/_SeqParser.py
chameleontools/SeqParser/__init__.py
chameleontools/Stealth/LICENSE.md
chameleontools/Stealth/README.md
chameleontools/Stealth/__init__.py
chameleontools/Stealth/_stealth.py
chameleontools/Stealth/_stealthClass.py
chameleontools/StealthParser/_StealthParser.py
chameleontools/StealthParser/__init__.py
chameleontools/__init__.py
chameleontools/_pstealth.py
chameleontools-1.0.1.dist-info/LICENSE
chameleontools-1.0.1.dist-info/METADATA
chameleontools-1.0.1.dist-info/WHEEL
chameleontools-1.0.1.dist-info/entry_points.txt
chameleontools-1.0.1.dist-info/RECORD
