Metadata-Version: 2.1
Name: chameleontools
Version: 1.0.1
Summary: A Stealth-based pipeline that optimizes plasmids for bacterial transformations in non-model organisms.
Home-page: https://gitlab.igem.org/2023/software-tools/ucsc
License: MIT
Author: Tyler Gaw
Author-email: tagaw@ucsc.edu
Requires-Python: >=3.10,<3.13
Classifier: License :: OSI Approved :: MIT License
Classifier: Programming Language :: Python :: 3
Classifier: Programming Language :: Python :: 3.10
Classifier: Programming Language :: Python :: 3.11
Requires-Dist: biopython (>=1.81,<2.0)
Requires-Dist: scipy (>=1.10.1,<2.0.0)
Requires-Dist: tqdm (>=4.66.1,<5.0.0)
Project-URL: Repository, https://gitlab.igem.org/2023/software-tools/ucsc
